README.md
setup.cfg
setup.py
cloudmersive_validate_api_client/__init__.py
cloudmersive_validate_api_client/api_client.py
cloudmersive_validate_api_client/configuration.py
cloudmersive_validate_api_client/rest.py
cloudmersive_validate_api_client.egg-info/PKG-INFO
cloudmersive_validate_api_client.egg-info/SOURCES.txt
cloudmersive_validate_api_client.egg-info/dependency_links.txt
cloudmersive_validate_api_client.egg-info/requires.txt
cloudmersive_validate_api_client.egg-info/top_level.txt
cloudmersive_validate_api_client/api/__init__.py
cloudmersive_validate_api_client/api/address_api.py
cloudmersive_validate_api_client/api/date_time_api.py
cloudmersive_validate_api_client/api/domain_api.py
cloudmersive_validate_api_client/api/email_api.py
cloudmersive_validate_api_client/api/ip_address_api.py
cloudmersive_validate_api_client/api/lead_enrichment_api.py
cloudmersive_validate_api_client/api/name_api.py
cloudmersive_validate_api_client/api/phone_number_api.py
cloudmersive_validate_api_client/api/text_input_api.py
cloudmersive_validate_api_client/api/user_agent_api.py
cloudmersive_validate_api_client/api/vat_api.py
cloudmersive_validate_api_client/models/__init__.py
cloudmersive_validate_api_client/models/address_get_servers_response.py
cloudmersive_validate_api_client/models/address_verify_syntax_only_response.py
cloudmersive_validate_api_client/models/bot_check_response.py
cloudmersive_validate_api_client/models/check_response.py
cloudmersive_validate_api_client/models/country_details.py
cloudmersive_validate_api_client/models/country_list_result.py
cloudmersive_validate_api_client/models/date_time_natural_language_parse_request.py
cloudmersive_validate_api_client/models/date_time_now_result.py
cloudmersive_validate_api_client/models/date_time_standardized_parse_request.py
cloudmersive_validate_api_client/models/date_time_standardized_parse_response.py
cloudmersive_validate_api_client/models/domain_quality_response.py
cloudmersive_validate_api_client/models/email_lead.py
cloudmersive_validate_api_client/models/first_name_validation_request.py
cloudmersive_validate_api_client/models/first_name_validation_response.py
cloudmersive_validate_api_client/models/full_email_validation_response.py
