Metadata-Version: 2.1
Name: cloudmersive-validate-api-client
Version: 3.2.5
Summary: validateapi
Home-page: https://www.cloudmersive.com/validate-api
Author-email: 
License: UNKNOWN
Keywords: Swagger,validateapi
Platform: UNKNOWN
